{
  "pluginId": "default",
  "version": "current",
  "label": "Next",
  "banner": null,
  "badge": false,
  "noIndex": false,
  "className": "docs-version-current",
  "isLast": true,
  "docsSidebars": {
    "pushChatSidebar": [
      {
        "type": "link",
        "label": "Intro to Push Chat",
        "href": "/docs/chat/",
        "docId": "chat/chat"
      },
      {
        "type": "link",
        "label": "Quickstart",
        "href": "/docs/chat/quickstart",
        "docId": "chat/docs-chat-quickstart"
      },
      {
        "type": "category",
        "label": "Build",
        "collapsed": false,
        "items": [
          {
            "type": "link",
            "label": "Get Started",
            "href": "/docs/chat/build/get-started",
            "docId": "chat/build/docs-chat-develop-get-started"
          },
          {
            "type": "link",
            "label": "Initialize User",
            "href": "/docs/chat/build/initialize-user",
            "docId": "chat/build/docs-chat-develop-initialize-user"
          },
          {
            "type": "link",
            "label": "Fetch Chats",
            "href": "/docs/chat/build/fetch-chats",
            "docId": "chat/build/docs-chat-develop-fetch-chats"
          },
          {
            "type": "link",
            "label": "Chat Requests",
            "href": "/docs/chat/build/chat-requests",
            "docId": "chat/build/docs-chat-develop-manage-chat-requests"
          },
          {
            "type": "link",
            "label": "Send Message",
            "href": "/docs/chat/build/send-message",
            "docId": "chat/build/docs-chat-develop-send-message"
          },
          {
            "type": "link",
            "label": "Types of Recipient",
            "href": "/docs/chat/build/types-of-recipient",
            "docId": "chat/build/docs-chat-develop-types-of-recipient"
          },
          {
            "type": "link",
            "label": "Create Group",
            "href": "/docs/chat/build/create-group",
            "docId": "chat/build/docs-chat-develop-create-groups"
          },
          {
            "type": "link",
            "label": "Group Requests",
            "href": "/docs/chat/build/group-requests",
            "docId": "chat/build/docs-chat-develop-group-requests"
          },
          {
            "type": "link",
            "label": "Group Permissions",
            "href": "/docs/chat/build/group-permissions",
            "docId": "chat/build/docs-chat-develop-group-permissions"
          },
          {
            "type": "link",
            "label": "Conditional Rules for Group",
            "href": "/docs/chat/build/conditional-rules-for-group",
            "docId": "chat/build/docs-chat-develop-conditional-rules-for-group"
          },
          {
            "type": "link",
            "label": "Manage Group",
            "href": "/docs/chat/build/manage-group",
            "docId": "chat/build/docs-chat-develop-manage-group"
          },
          {
            "type": "link",
            "label": "Stream Chats",
            "href": "/docs/chat/build/stream-chats",
            "docId": "chat/build/docs-chat-develop-stream-chats"
          },
          {
            "type": "link",
            "label": "All API Calls",
            "href": "/docs/chat/build/all-api-calls",
            "docId": "chat/build/dev-chat-all-api-calls"
          }
        ],
        "collapsible": true,
        "href": "/docs/chat/build"
      },
      {
        "type": "category",
        "label": "Message Types",
        "collapsed": false,
        "items": [
          {
            "type": "link",
            "label": "Text",
            "href": "/docs/chat/message-types/text",
            "docId": "chat/message-types/docs-chat-message-type-text"
          },
          {
            "type": "link",
            "label": "Image",
            "href": "/docs/chat/message-types/image",
            "docId": "chat/message-types/docs-chat-message-type-image"
          },
          {
            "type": "link",
            "label": "File",
            "href": "/docs/chat/message-types/file",
            "docId": "chat/message-types/docs-chat-message-type-file"
          },
          {
            "type": "link",
            "label": "Media Embed",
            "href": "/docs/chat/message-types/media-embed",
            "docId": "chat/message-types/docs-chat-message-type-media-embed"
          },
          {
            "type": "link",
            "label": "Reaction",
            "href": "/docs/chat/message-types/reaction",
            "docId": "chat/message-types/docs-chat-message-type-reaction"
          },
          {
            "type": "link",
            "label": "Meta",
            "href": "/docs/chat/message-types/meta",
            "docId": "chat/message-types/docs-chat-message-type-meta"
          }
        ],
        "collapsible": true,
        "href": "/docs/chat/message-types"
      },
      {
        "type": "category",
        "label": "UI Components",
        "collapsed": true,
        "items": [
          {
            "type": "link",
            "label": "Usecases",
            "href": "/docs/chat/ui-components/UseCase",
            "docId": "chat/ui-components/UseCase"
          },
          {
            "type": "category",
            "label": "Advanced",
            "collapsible": true,
            "collapsed": false,
            "items": [
              {
                "type": "link",
                "label": "ChatUIProvider",
                "href": "/docs/chat/ui-components/Advanced/ChatUIProvider",
                "docId": "chat/ui-components/Advanced/ChatUIProvider"
              },
              {
                "type": "link",
                "label": "ChatViewBubble",
                "href": "/docs/chat/ui-components/Advanced/ChatViewBubble",
                "docId": "chat/ui-components/Advanced/ChatViewBubble"
              },
              {
                "type": "link",
                "label": "ChatViewList",
                "href": "/docs/chat/ui-components/Advanced/ChatViewList",
                "docId": "chat/ui-components/Advanced/ChatViewList"
              },
              {
                "type": "link",
                "label": "ChatProfile",
                "href": "/docs/chat/ui-components/Advanced/ChatProfile",
                "docId": "chat/ui-components/Advanced/ChatProfile"
              },
              {
                "type": "link",
                "label": "MessageInput",
                "href": "/docs/chat/ui-components/Advanced/MessageInput",
                "docId": "chat/ui-components/Advanced/MessageInput"
              },
              {
                "type": "link",
                "label": "ChatViewComponent",
                "href": "/docs/chat/ui-components/Advanced/ChatViewComponent",
                "docId": "chat/ui-components/Advanced/ChatViewComponent"
              },
              {
                "type": "link",
                "label": "Theme",
                "href": "/docs/chat/ui-components/Advanced/Theme",
                "docId": "chat/ui-components/Advanced/Theme"
              }
            ]
          }
        ],
        "collapsible": true,
        "href": "/docs/chat/ui-components"
      },
      {
        "type": "category",
        "label": "Tutorials",
        "collapsed": true,
        "items": [
          {
            "type": "link",
            "label": "Push SDK Playground",
            "href": "/docs/chat/tutorials/push-sdk-playground",
            "docId": "chat/tutorials/docs-chat-push-sdk-playground"
          },
          {
            "type": "link",
            "label": "Push SDK React Playground",
            "href": "/docs/chat/tutorials/push-react-component-playground-example",
            "docId": "chat/tutorials/docs-chat-tutorials-push-react-component-playground-example"
          }
        ],
        "collapsible": true,
        "href": "/docs/chat/tutorials"
      },
      {
        "type": "category",
        "label": "Concepts",
        "collapsed": true,
        "items": [
          {
            "type": "link",
            "label": "Push Chat Architecture",
            "href": "/docs/chat/concepts/push-chat-architecture",
            "docId": "chat/concepts/docs-chat-concepts-architecture-overview"
          },
          {
            "type": "link",
            "label": "Encryption Version in Push Chat",
            "href": "/docs/chat/concepts/encryption-version-in-push-chat",
            "docId": "chat/concepts/docs-chat-encryption-version-in-push-chat"
          }
        ],
        "collapsible": true,
        "href": "/docs/chat/concepts"
      }
    ]
  },
  "docs": {
    "chat/build/dev-chat-all-api-calls": {
      "id": "chat/build/dev-chat-all-api-calls",
      "title": "All API Calls",
      "description": "This tutorial is designed to get you up and going by providing a step wise guide to use and explore the Push SDK.",
      "sidebar": "pushChatSidebar"
    },
    "chat/build/docs-chat-develop-conditional-rules-for-group": {
      "id": "chat/build/docs-chat-develop-conditional-rules-for-group",
      "title": "Conditional Rules for Group",
      "description": "Conditional gating allows you to define rules for the members of the group for different privileges / permissions such as entry or chat. It is driven by Push Chat rules engine which is inspired by json rules engine and allows you to create powerful dynamics guiding communication for your community. Some examples of what you can achieve with it —",
      "sidebar": "pushChatSidebar"
    },
    "chat/build/docs-chat-develop-create-groups": {
      "id": "chat/build/docs-chat-develop-create-groups",
      "title": "Create Group",
      "description": "Group chat is the latest exciting addition to Push Chat, for the first time ever, web3 users are finally able to talk to each other in web3 native groups and have fine-grained controls over them allowing new ways by which community can be engaged besides adding new utilities to your token. Group chat enables protocols or web3 projects to create —",
      "sidebar": "pushChatSidebar"
    },
    "chat/build/docs-chat-develop-fetch-chats": {
      "id": "chat/build/docs-chat-develop-fetch-chats",
      "title": "Fetch Chats",
      "description": "These APIs are useful for fetching list of all chats (or chat requests) that a user might have, along with providing calls to get latest message or historical messages between two users (or from a group).",
      "sidebar": "pushChatSidebar"
    },
    "chat/build/docs-chat-develop-get-started": {
      "id": "chat/build/docs-chat-develop-get-started",
      "title": "Get Started",
      "description": "Push Chat enables web3 native messaging between wallets, groups, NFTs or even conditional (gated) groups. To do so, you will be using Push SDK API that will abstract away the complexity of authentication, encryption, signing, sending and receiving of messages.",
      "sidebar": "pushChatSidebar"
    },
    "chat/build/docs-chat-develop-group-permissions": {
      "id": "chat/build/docs-chat-develop-group-permissions",
      "title": "Group Permissions",
      "description": "These APIs help in validating if you have permissions for a gated group.",
      "sidebar": "pushChatSidebar"
    },
    "chat/build/docs-chat-develop-group-requests": {
      "id": "chat/build/docs-chat-develop-group-requests",
      "title": "Group Requests",
      "description": "This section deals with API calls related to joining or leaving a group.",
      "sidebar": "pushChatSidebar"
    },
    "chat/build/docs-chat-develop-initialize-user": {
      "id": "chat/build/docs-chat-develop-initialize-user",
      "title": "Initialize User",
      "description": "Before you can start sending messages, or create conditional access group for your community, or send those chat requests to Vitalik.eth. you will need to initialize a user or re-authenticate the user. To do so you will use PushAPI.initialize call from @pushprotocol/restapi package.",
      "sidebar": "pushChatSidebar"
    },
    "chat/build/docs-chat-develop-manage-chat-requests": {
      "id": "chat/build/docs-chat-develop-manage-chat-requests",
      "title": "Chat Requests",
      "description": "You can send a message using chat.send API to either an existing chat connection or to initiate a new chat to a wallet you haven't chatted with before (which is called sending a chat request).",
      "sidebar": "pushChatSidebar"
    },
    "chat/build/docs-chat-develop-manage-group": {
      "id": "chat/build/docs-chat-develop-manage-group",
      "title": "Manage Group",
      "description": "This section covers all APIs related to managing groups including adding / removing members or admins, updating group info or fetching group info.",
      "sidebar": "pushChatSidebar"
    },
    "chat/build/docs-chat-develop-send-message": {
      "id": "chat/build/docs-chat-develop-send-message",
      "title": "Send Message",
      "description": "Push Chat doesn't require a user to be on the network for you to send message 😀. Instead, it gives you the freedom to send a nudge to an account or a message (or a meme).",
      "sidebar": "pushChatSidebar"
    },
    "chat/build/docs-chat-develop-stream-chats": {
      "id": "chat/build/docs-chat-develop-stream-chats",
      "title": "Stream Chats",
      "description": "These APIs enable you to receive chat payloads or chat request / group invites in real time without polling the API. Push Chat achieves this by the use of sockets.",
      "sidebar": "pushChatSidebar"
    },
    "chat/build/docs-chat-develop-types-of-recipient": {
      "id": "chat/build/docs-chat-develop-types-of-recipient",
      "title": "Types of Recipient",
      "description": "Push Chat is chain agnostic and even supports messaging wallet addresses, NFT addresses, all evms (and even non-EVM in the future). Below is the list of evergrowing standards that Push Chat is compatible with, either of which you can use as per your requirements  —",
      "sidebar": "pushChatSidebar"
    },
    "chat/chat": {
      "id": "chat/chat",
      "title": "Intro to Push Chat",
      "description": "Push Chat is a web3 messaging protocol that allows wallet addresses to send and receive messages without the need for traditional personal identifiers like phone numbers, email addresses, etc. It offers an enhanced layer of security and privacy compared to conventional messaging apps and allows for experiences that can only be achieved by native web3 messaging including the ability to create token gated experiences, chat anonymously, tie your communication to your keys and more!",
      "sidebar": "pushChatSidebar"
    },
    "chat/concepts/docs-chat-concepts-architecture-overview": {
      "id": "chat/concepts/docs-chat-concepts-architecture-overview",
      "title": "Push Chat Architecture",
      "description": "Push Chat is a web3 messaging protocol that enables wallet addresses to send and receive messages, offering a secure and privacy-focused alternative to traditional messaging apps. By leveraging blockchain technology, users can communicate directly via their wallet addresses without personal identifiers like phone numbers, email addresses, etc.",
      "sidebar": "pushChatSidebar"
    },
    "chat/concepts/docs-chat-encryption-version-in-push-chat": {
      "id": "chat/concepts/docs-chat-encryption-version-in-push-chat",
      "title": "Encryption Version in Push Chat",
      "description": "Each Push profile or user of Push Chat has a PGP key that is created locally and stored encrypted on Push nodes. Push SDK during initialization automatically decrypts your key by asking you to sign a nonce which is used to derive the signature that is applied to encrypt or decrypt your PGP keys.",
      "sidebar": "pushChatSidebar"
    },
    "chat/docs-chat-build-section": {
      "id": "chat/docs-chat-build-section",
      "title": "Build",
      "description": "This section covers everything you will require from Push SDK to create any functionality or features related to Push Chat.",
      "sidebar": "pushChatSidebar"
    },
    "chat/docs-chat-concepts-section": {
      "id": "chat/docs-chat-concepts-section",
      "title": "Concepts",
      "description": "Brush up on some crucial concepts that will help you understand Push Chat better.",
      "sidebar": "pushChatSidebar"
    },
    "chat/docs-chat-message-types-section": {
      "id": "chat/docs-chat-message-types-section",
      "title": "Message Types",
      "description": "Each message of Push Chat is a json payload that carries with it a message type and some parameters that enable each frontend that integrates Push Chat to understand and display various message types.",
      "sidebar": "pushChatSidebar"
    },
    "chat/docs-chat-quickstart": {
      "id": "chat/docs-chat-quickstart",
      "title": "Quickstart",
      "description": "Everything you will need to get up and running in 2 mins or less!",
      "sidebar": "pushChatSidebar"
    },
    "chat/docs-chat-tutorials-section": {
      "id": "chat/docs-chat-tutorials-section",
      "title": "Tutorials",
      "description": "Find all tutorials related to Push Chat and more!",
      "sidebar": "pushChatSidebar"
    },
    "chat/docs-chat-ui-components-section": {
      "id": "chat/docs-chat-ui-components-section",
      "title": "UI Components",
      "description": "This Section will show you how you can easily integrate Push Chat, Group Chat and Token Gated Group Chat in your dapp with just few lines of code using our components from @pushprotocol/uiweb",
      "sidebar": "pushChatSidebar"
    },
    "chat/message-types/docs-chat-message-type-file": {
      "id": "chat/message-types/docs-chat-message-type-file",
      "title": "File",
      "description": "Enables sending single file or attachement as a message. You will need to pass the file as base64. Base64 is a method for encoding binary data into ASCII text.",
      "sidebar": "pushChatSidebar"
    },
    "chat/message-types/docs-chat-message-type-image": {
      "id": "chat/message-types/docs-chat-message-type-image",
      "title": "Image",
      "description": "Enables sending a single image as a messages to the recipient. You will need to pass the image as base64. Base64 is a method for encoding binary data into ASCII text.",
      "sidebar": "pushChatSidebar"
    },
    "chat/message-types/docs-chat-message-type-media-embed": {
      "id": "chat/message-types/docs-chat-message-type-media-embed",
      "title": "Media Embed",
      "description": "Enables sending a image URLs or media URLs as a message. You can send GIFs, Tweets, Youtube links, etc. Simply pass in the URL of the media as content.",
      "sidebar": "pushChatSidebar"
    },
    "chat/message-types/docs-chat-message-type-meta": {
      "id": "chat/message-types/docs-chat-message-type-meta",
      "title": "Meta",
      "description": "Enables sending arbitary meta actions in a group. This message type has some rules and it's recommeneded to not interact directly with this message type as Push SDK will handle it for you. It's documentated just for the curious minds.",
      "sidebar": "pushChatSidebar"
    },
    "chat/message-types/docs-chat-message-type-reaction": {
      "id": "chat/message-types/docs-chat-message-type-reaction",
      "title": "Reaction",
      "description": "Enables reacting by using emoji to a message.",
      "sidebar": "pushChatSidebar"
    },
    "chat/message-types/docs-chat-message-type-text": {
      "id": "chat/message-types/docs-chat-message-type-text",
      "title": "Text",
      "description": "Enables sending simple text messages to the recipient.",
      "sidebar": "pushChatSidebar"
    },
    "chat/tutorials/docs-chat-push-sdk-playground": {
      "id": "chat/tutorials/docs-chat-push-sdk-playground",
      "title": "Push SDK Playground",
      "description": "This tutorial is designed to get you up and going by providing playground containing all API calls coverage for Push SDK. Checkout Push SDK example that utlizes @pushprotocol/restapi and @pushprotocol/socket for more info!",
      "sidebar": "pushChatSidebar"
    },
    "chat/tutorials/docs-chat-tutorials-push-react-component-playground-example": {
      "id": "chat/tutorials/docs-chat-tutorials-push-react-component-playground-example",
      "title": "Push SDK React Playground",
      "description": "This tutorial is designed to get you up and going by providing playground containing all frontend React components coverage. Checkout Push SDK React frontend example that utlizes @pushprotocol/uiweb @pushprotocol/restapi and @pushprotocol/socket for more info!",
      "sidebar": "pushChatSidebar"
    },
    "chat/ui-components/Advanced/ChatProfile": {
      "id": "chat/ui-components/Advanced/ChatProfile",
      "title": "ChatProfile",
      "description": "Empower User Interaction: Showcase Wallet Addresses, Group Names, and Member Management with ChatProfile in Your Dapp.",
      "sidebar": "pushChatSidebar"
    },
    "chat/ui-components/Advanced/ChatUIProvider": {
      "id": "chat/ui-components/Advanced/ChatUIProvider",
      "title": "ChatUIProvider",
      "description": "Enhance State Management: Boost Your Component's Functionality by Wrapping it with ChatUIProvider.",
      "sidebar": "pushChatSidebar"
    },
    "chat/ui-components/Advanced/ChatViewBubble": {
      "id": "chat/ui-components/Advanced/ChatViewBubble",
      "title": "ChatViewBubble",
      "description": "Simplify Development: Instantly Integrate Pre-built Chat Bubble UI for Your Dapp",
      "sidebar": "pushChatSidebar"
    },
    "chat/ui-components/Advanced/ChatViewComponent": {
      "id": "chat/ui-components/Advanced/ChatViewComponent",
      "title": "ChatViewComponent",
      "description": "Effortless Messaging Integration: Add a Complete Chat Interface to Your Dapp with ChatViewComponent.",
      "sidebar": "pushChatSidebar"
    },
    "chat/ui-components/Advanced/ChatViewList": {
      "id": "chat/ui-components/Advanced/ChatViewList",
      "title": "ChatViewList",
      "description": "Streamlined Chat List Integration: Easily Add a Message List to Your Dapp with Built-in Pagination",
      "sidebar": "pushChatSidebar"
    },
    "chat/ui-components/Advanced/MessageInput": {
      "id": "chat/ui-components/Advanced/MessageInput",
      "title": "MessageInput",
      "description": "Versatile Message Input Integration: Enable Text, Image, File, and Gif Sharing in Your Dapp with MessageInput.",
      "sidebar": "pushChatSidebar"
    },
    "chat/ui-components/Advanced/Theme": {
      "id": "chat/ui-components/Advanced/Theme",
      "title": "Theme",
      "description": "",
      "sidebar": "pushChatSidebar"
    },
    "chat/ui-components/UseCase": {
      "id": "chat/ui-components/UseCase",
      "title": "Usecases",
      "description": "Streamline Chat Integration for Developers: Say goodbye to the hassles of UI design and API calls. With our web components available in the @pushprotocol/uiweb package, you can effortlessly integrate push chat functionality into your dapp using just a few lines of code.",
      "sidebar": "pushChatSidebar"
    },
    "documentation-hub": {
      "id": "documentation-hub",
      "title": "Documentation Hub",
      "description": ""
    }
  }
}