{
  "permalink": "/blog/4-reasons-to-seperate-your-dapp-communication-and-execution-layers",
  "source": "@site/blog/2023-09-21-4-reasons-to-seperate/index.md",
  "title": "4 Reasons To Separate Your dApp’s Communication and Execution Layers",
  "description": "Docusaurus Image",
  "date": "2023-09-21T00:00:00.000Z",
  "formattedDate": "September 21, 2023",
  "tags": [
    {
      "label": "Pushprotocol",
      "permalink": "/blog/tags/pushprotocol"
    },
    {
      "label": "Web3",
      "permalink": "/blog/tags/web-3"
    },
    {
      "label": "Blockchain Technology",
      "permalink": "/blog/tags/blockchain-technology"
    }
  ],
  "readingTime": 5.81,
  "hasTruncateMarker": true,
  "authors": [
    {
      "name": "Push Protocol",
      "url": "https://push.org",
      "imageURL": "/assets/blog/authors/authorpush.png",
      "key": "push"
    }
  ],
  "frontMatter": {
    "slug": "4-reasons-to-seperate-your-dapp-communication-and-execution-layers",
    "title": "4 Reasons To Separate Your dApp’s Communication and Execution Layers",
    "authors": [
      "push"
    ],
    "tags": [
      "Pushprotocol",
      "Web3",
      "Blockchain Technology"
    ]
  },
  "nextItem": {
    "title": "Deep-dive into Push Snaps Features & Getting Started 🛠️",
    "permalink": "/blog/deep-dive-into-push-snaps-features-and-getting-started-all-the-technical-specifications-and-getting-started-tips-you-need"
  }
}