{
  "permalink": "/blog/what-is-erc-6551-and-how-s-it-better-than-erc-721",
  "source": "@site/blog/2023-06-13-what-is-erc-6551/index.md",
  "title": "What is ERC-6551 and How’s It Better than ERC-721?",
  "description": "Docusaurus Image",
  "date": "2023-06-13T00:00:00.000Z",
  "formattedDate": "June 13, 2023",
  "tags": [
    {
      "label": "Erc6551",
      "permalink": "/blog/tags/erc-6551"
    },
    {
      "label": "Eip",
      "permalink": "/blog/tags/eip"
    },
    {
      "label": "Ethereum",
      "permalink": "/blog/tags/ethereum"
    },
    {
      "label": "Nft",
      "permalink": "/blog/tags/nft"
    },
    {
      "label": "Web Tools",
      "permalink": "/blog/tags/web-tools"
    }
  ],
  "readingTime": 4.765,
  "hasTruncateMarker": true,
  "authors": [
    {
      "name": "Push Protocol",
      "url": "https://push.org",
      "imageURL": "/assets/blog/authors/authorpush.png",
      "key": "push"
    }
  ],
  "frontMatter": {
    "slug": "what-is-erc-6551-and-how-s-it-better-than-erc-721",
    "title": "What is ERC-6551 and How’s It Better than ERC-721?",
    "authors": [
      "push"
    ],
    "tags": [
      "Erc6551",
      "Eip",
      "Ethereum",
      "Nft",
      "Web Tools"
    ]
  },
  "prevItem": {
    "title": "$100,000 of Push x ImmuneFi Bug Bounty Program goes Live 🪲",
    "permalink": "/blog/100-000-of-push-x-immune-fi-bug-bounty-program-goes-live"
  },
  "nextItem": {
    "title": "Unleashing a New Era of Social Networking | Push x SOCLLY🌿",
    "permalink": "/blog/unleashing-a-new-era-of-social-networking-push-x-soclly"
  }
}